{
    "tper_2018": "Total Personas",
    "tvivienda": "Total viviendas",
    "tp19_gas_1": "Porcentaje de personas con acceso a gas",
    "tp19_ee_1": "Porcentaje de personas con acceso a energ\u00eda el\u00e9ctrica",
    "tp19_alc_1": "Porcentaje de personas con acceso a alcantarillado",
    "tp19_acu_1": "Porcentaje de personas con acceso acueducto",
    "tp19_inte1": "Porcentaje de personas con acceso a internet",
    "tp19_ee_e1": "Porcentaje de hogares estrato 1",
    "tp19_ee_e2": "Porcentaje de hogares estrato 2",
    "tp19_ee_e3": "Porcentaje de hogares estrato 3",
    "tp19_ee_e4": "Porcentaje de hogares estrato 4",
    "tp19_ee_e5": "Porcentaje de hogares estrato 5",
    "tp19_ee_e6": "Porcentaje de hogares estrato 6",
    "dens_emp_m2": "Densidad empresarial",
    "avaluo_prom_imp": "Avaluo promedio del impuesto predial en pesos colombianos por metro cuadrado",
    "avaluo_tot_imp": "Avaluo total del impuesto predial en pesos colombianos por metro cuadrado",
    "riesgo_pluv_alto": "Riesgo pluvial alto",
    "riesgo_pluv_mod": "Riesgo pluvial moderado",
    "min_dist": "Distancia m\u00ednima a un paraderos en metros",
    "avg_dist": "Distancia promedio a un paradero en metros",
    "n_paraderos": "N\u00famero de paraderos",
    "n_rutas": "N\u00famero de rutas",
    "n_afiliados": "N\u00famero de afiliados por manzana",
    "hta": "N\u00famero de afiliados con condici\u00f3n Hiper Tensi\u00f3n Arterial",
    "dm": "N\u00famero de afiliados con condici\u00f3n Diabetes Melitus",
    "epoc": "N\u00famero de afiliados con condici\u00f3n EPOC"
}